{
  "generated_at": "2026-05-24T19:57:02.658288",
  "version": "3.112",
  "script_hash": "a60c2ee19b34",
  "scan_hours": 72,
  "retention_days": 14,
  "activities": [
    {
      "activity_id": "i149690889",
      "date": "2026-05-19",
      "type": "Ride",
      "name": "\u00c5mot Maantiepy\u00f6r\u00e4ily",
      "interval_summary": null,
      "intervals": [
        {
          "type": "RECOVERY",
          "duration_secs": 3475,
          "avg_power": 146,
          "max_power": 404,
          "avg_hr": 107,
          "max_hr": 144,
          "avg_cadence": 79.43515,
          "zone": 1,
          "training_load": 28.328789,
          "decoupling": -24.174992
        }
      ]
    },
    {
      "activity_id": "i148595640",
      "date": "2026-05-15",
      "type": "Ride",
      "name": "Lloret de Mar - 3x15 over under",
      "interval_summary": [
        "10x 86s 358w",
        "4x 29s 393w",
        "1x 12s 533w",
        "1x 60s 343w",
        "1x 3m28s 243w"
      ],
      "intervals": [
        {
          "type": "RECOVERY",
          "duration_secs": 4843,
          "avg_power": 114,
          "max_power": 556,
          "avg_hr": 94,
          "max_hr": 129,
          "avg_cadence": 55.766174,
          "zone": 1,
          "training_load": 14.273988
        },
        {
          "type": "WORK",
          "label": "86s@358w94rpm",
          "duration_secs": 77,
          "avg_power": 344,
          "max_power": 404,
          "avg_hr": 131,
          "max_hr": 140,
          "avg_cadence": 89.90909,
          "zone": 5,
          "training_load": 2.4430957,
          "decoupling": 5.725221
        },
        {
          "type": "RECOVERY",
          "duration_secs": 61,
          "avg_power": 208,
          "max_power": 322,
          "avg_hr": 133,
          "max_hr": 140,
          "avg_cadence": 79.21311,
          "zone": 2,
          "training_load": 1.0508204,
          "decoupling": -5.6531878
        },
        {
          "type": "WORK",
          "label": "86s@358w94rpm",
          "duration_secs": 89,
          "avg_power": 354,
          "max_power": 447,
          "avg_hr": 134,
          "max_hr": 143,
          "avg_cadence": 89.4382,
          "zone": 5,
          "training_load": 2.7581694,
          "decoupling": 13.263328
        },
        {
          "type": "RECOVERY",
          "duration_secs": 59,
          "avg_power": 213,
          "max_power": 369,
          "avg_hr": 135,
          "max_hr": 143,
          "avg_cadence": 74.44068,
          "zone": 2,
          "training_load": 1.032564,
          "decoupling": -16.323248
        },
        {
          "type": "WORK",
          "label": "86s@358w94rpm",
          "duration_secs": 91,
          "avg_power": 349,
          "max_power": 423,
          "avg_hr": 138,
          "max_hr": 145,
          "avg_cadence": 94.47253,
          "zone": 5,
          "training_load": 2.770311,
          "decoupling": 9.557478
        },
        {
          "type": "RECOVERY",
          "duration_secs": 58,
          "avg_power": 159,
          "max_power": 314,
          "avg_hr": 134,
          "max_hr": 145,
          "avg_cadence": 91.22414,
          "zone": 1,
          "training_load": 0.81789064,
          "decoupling": -26.350348
        },
        {
          "type": "WORK",
          "label": "86s@358w94rpm",
          "duration_secs": 92,
          "avg_power": 353,
          "max_power": 468,
          "avg_hr": 139,
          "max_hr": 149,
          "avg_cadence": 97.065216,
          "zone": 5,
          "training_load": 2.8342957,
          "decoupling": 17.558569
        },
        {
          "type": "RECOVERY",
          "duration_secs": 60,
          "avg_power": 239,
          "max_power": 359,
          "avg_hr": 147,
          "max_hr": 151,
          "avg_cadence": 77.25,
          "zone": 2,
          "training_load": 1.2130371,
          "decoupling": 3.599532
        },
        {
          "type": "WORK",
          "label": "86s@358w94rpm",
          "duration_secs": 83,
          "avg_power": 356,
          "max_power": 449,
          "avg_hr": 143,
          "max_hr": 151,
          "avg_cadence": 94.180725,
          "zone": 5,
          "training_load": 2.602756,
          "decoupling": 10.1719
        },
        {
          "type": "RECOVERY",
          "duration_secs": 69,
          "avg_power": 87,
          "max_power": 455,
          "avg_hr": 127,
          "max_hr": 152,
          "avg_cadence": 42.52174,
          "zone": 1,
          "training_load": 0.80202395,
          "decoupling": 12.0714855
        },
        {
          "type": "WORK",
          "label": "86s@358w94rpm",
          "duration_secs": 87,
          "avg_power": 382,
          "max_power": 573,
          "avg_hr": 142,
          "max_hr": 152,
          "avg_cadence": 98.82758,
          "zone": 5,
          "training_load": 3.0078297,
          "decoupling": 11.9058075
        },
        {
          "type": "RECOVERY",
          "duration_secs": 531,
          "avg_power": 172,
          "max_power": 549,
          "avg_hr": 121,
          "max_hr": 153,
          "avg_cadence": 83.46704,
          "zone": 1,
          "training_load": 7.752969,
          "decoupling": -52.11611
        },
        {
          "type": "WORK",
          "label": "29s@393w100rpm",
          "duration_secs": 31,
          "avg_power": 399,
          "max_power": 500,
          "avg_hr": 133,
          "max_hr": 140,
          "avg_cadence": 102.258064,
          "zone": 6,
          "training_load": 0.983584,
          "decoupling": 11.992998
        },
        {
          "type": "RECOVERY",
          "duration_secs": 336,
          "avg_power": 243,
          "max_power": 713,
          "avg_hr": 137,
          "max_hr": 151,
          "avg_cadence": 80.31544,
          "zone": 3,
          "training_load": 7.226888,
          "decoupling": 1.4839442
        },
        {
          "type": "WORK",
          "label": "12s@533w85rpm",
          "duration_secs": 12,
          "avg_power": 533,
          "max_power": 693,
          "avg_hr": 119,
          "max_hr": 128,
          "avg_cadence": 84.916664,
          "zone": 7,
          "training_load": 0.08862305,
          "decoupling": 32.467335
        },
        {
          "type": "RECOVERY",
          "duration_secs": 3,
          "avg_power": 425,
          "max_power": 446,
          "avg_hr": 130,
          "max_hr": 132,
          "avg_cadence": 95.333336,
          "zone": 6,
          "training_load": 0.052503254,
          "decoupling": 8.972033
        },
        {
          "type": "WORK",
          "label": "29s@393w100rpm",
          "duration_secs": 28,
          "avg_power": 393,
          "max_power": 449,
          "avg_hr": 142,
          "max_hr": 150,
          "avg_cadence": 99.89286,
          "zone": 6,
          "training_load": 1.227461,
          "decoupling": 11.708515
        },
        {
          "type": "RECOVERY",
          "duration_secs": 75,
          "avg_power": 206,
          "max_power": 399,
          "avg_hr": 143,
          "max_hr": 153,
          "avg_cadence": 85.293335,
          "zone": 2,
          "training_load": 1.3965658,
          "decoupling": -26.772911
        },
        {
          "type": "WORK",
          "label": "86s@358w94rpm",
          "duration_secs": 76,
          "avg_power": 360,
          "max_power": 480,
          "avg_hr": 146,
          "max_hr": 154,
          "avg_cadence": 98.0,
          "zone": 5,
          "training_load": 2.3972862,
          "decoupling": 11.122612
        },
        {
          "type": "RECOVERY",
          "duration_secs": 74,
          "avg_power": 164,
          "max_power": 324,
          "avg_hr": 142,
          "max_hr": 155,
          "avg_cadence": 83.77027,
          "zone": 1,
          "training_load": 1.2747656,
          "decoupling": 2.102846
        },
        {
          "type": "WORK",
          "label": "86s@358w94rpm",
          "duration_secs": 89,
          "avg_power": 351,
          "max_power": 451,
          "avg_hr": 143,
          "max_hr": 153,
          "avg_cadence": 92.685394,
          "zone": 5,
          "training_load": 2.7094252,
          "decoupling": 16.374584
        },
        {
          "type": "RECOVERY",
          "duration_secs": 780,
          "avg_power": 104,
          "max_power": 558,
          "avg_hr": 109,
          "max_hr": 152,
          "avg_cadence": 63.66421,
          "zone": 1,
          "training_load": 4.5668583,
          "decoupling": -33.596123
        },
        {
          "type": "WORK",
          "label": "60s@343w90rpm",
          "duration_secs": 60,
          "avg_power": 343,
          "max_power": 449,
          "avg_hr": 138,
          "max_hr": 144,
          "avg_cadence": 90.38333,
          "zone": 5,
          "training_load": 1.7940104,
          "decoupling": 8.736804
        },
        {
          "type": "RECOVERY",
          "duration_secs": 237,
          "avg_power": 248,
          "max_power": 677,
          "avg_hr": 132,
          "max_hr": 144,
          "avg_cadence": 86.31797,
          "zone": 3,
          "training_load": 4.736166,
          "decoupling": 17.569305
        },
        {
          "type": "WORK",
          "label": "86s@358w94rpm",
          "duration_secs": 87,
          "avg_power": 358,
          "max_power": 445,
          "avg_hr": 140,
          "max_hr": 152,
          "avg_cadence": 92.70115,
          "zone": 5,
          "training_load": 2.8253288,
          "decoupling": 14.235565
        },
        {
          "type": "RECOVERY",
          "duration_secs": 63,
          "avg_power": 175,
          "max_power": 316,
          "avg_hr": 138,
          "max_hr": 151,
          "avg_cadence": 80.38095,
          "zone": 1,
          "training_load": 0.93577147,
          "decoupling": -23.432478
        },
        {
          "type": "WORK",
          "label": "86s@358w94rpm",
          "duration_secs": 91,
          "avg_power": 370,
          "max_power": 444,
          "avg_hr": 144,
          "max_hr": 155,
          "avg_cadence": 93.82417,
          "zone": 5,
          "training_load": 3.0760143,
          "decoupling": 13.299262
        },
        {
          "type": "RECOVERY",
          "duration_secs": 82,
          "avg_power": 238,
          "max_power": 411,
          "avg_hr": 141,
          "max_hr": 154,
          "avg_cadence": 83.46342,
          "zone": 2,
          "training_load": 1.4125781,
          "decoupling": -59.80571
        },
        {
          "type": "WORK",
          "label": "29s@393w100rpm",
          "duration_secs": 29,
          "avg_power": 425,
          "max_power": 534,
          "avg_hr": 145,
          "max_hr": 150,
          "avg_cadence": 98.89655,
          "zone": 6,
          "training_load": 1.1419458,
          "decoupling": -12.986086
        },
        {
          "type": "RECOVERY",
          "duration_secs": 1380,
          "avg_power": 182,
          "max_power": 549,
          "avg_hr": 119,
          "max_hr": 155,
          "avg_cadence": 85.60725,
          "zone": 2,
          "training_load": 17.79056,
          "decoupling": 6.6695137
        },
        {
          "type": "WORK",
          "label": "208s@243w81rpm",
          "duration_secs": 208,
          "avg_power": 243,
          "max_power": 316,
          "avg_hr": 127,
          "max_hr": 132,
          "avg_cadence": 80.99039,
          "zone": 3,
          "training_load": 3.25,
          "decoupling": 4.1875515
        },
        {
          "type": "RECOVERY",
          "duration_secs": 199,
          "avg_power": 150,
          "max_power": 392,
          "avg_hr": 120,
          "max_hr": 133,
          "avg_cadence": 87.658295,
          "zone": 1,
          "training_load": 1.8675684,
          "decoupling": -58.814674
        },
        {
          "type": "WORK",
          "label": "29s@393w100rpm",
          "duration_secs": 29,
          "avg_power": 356,
          "max_power": 468,
          "avg_hr": 131,
          "max_hr": 139,
          "avg_cadence": 97.86207,
          "zone": 5,
          "training_load": 0.54000545,
          "decoupling": 18.695305
        },
        {
          "type": "RECOVERY",
          "duration_secs": 613,
          "avg_power": 76,
          "max_power": 1042,
          "avg_hr": 102,
          "max_hr": 141,
          "avg_cadence": 45.50874,
          "zone": 1,
          "training_load": 5.551263,
          "decoupling": 15.23031
        }
      ]
    },
    {
      "activity_id": "i148234477",
      "date": "2026-05-14",
      "type": "Ride",
      "name": "Calonge Maantiepy\u00f6r\u00e4ily",
      "interval_summary": null,
      "intervals": [
        {
          "type": "RECOVERY",
          "duration_secs": 589,
          "avg_power": 131,
          "max_power": 439,
          "avg_hr": 105,
          "max_hr": 118,
          "avg_cadence": 60.810055,
          "zone": 1,
          "training_load": 3.7516427,
          "decoupling": 1.1786821
        }
      ]
    },
    {
      "activity_id": "i148232231",
      "date": "2026-05-14",
      "type": "Ride",
      "name": "Mont-Ras - 3x3x12 tunti jonka toinen puolikas sptintti joka 4",
      "interval_summary": [
        "13x 7s 923w",
        "2x 3m5s 248w",
        "1x 4m52s 248w",
        "1x 3m42s 253w"
      ],
      "intervals": [
        {
          "type": "RECOVERY",
          "duration_secs": 8839,
          "avg_power": 102,
          "max_power": 418,
          "avg_hr": 91,
          "max_hr": 122,
          "avg_cadence": 60.49346,
          "zone": 1,
          "training_load": 30.435953,
          "decoupling": -18.187717
        },
        {
          "type": "WORK",
          "label": "7s@923w104rpm",
          "duration_secs": 5,
          "avg_power": 859,
          "max_power": 950,
          "avg_hr": 106,
          "max_hr": 109,
          "avg_cadence": 98.4,
          "zone": 7,
          "training_load": 0.046923827,
          "decoupling": 3.4666302
        },
        {
          "type": "RECOVERY",
          "duration_secs": 69,
          "avg_power": 147,
          "max_power": 1052,
          "avg_hr": 112,
          "max_hr": 122,
          "avg_cadence": 65.21739,
          "zone": 1,
          "training_load": 0.5930436,
          "decoupling": -8.943349
        },
        {
          "type": "WORK",
          "label": "7s@923w104rpm",
          "duration_secs": 5,
          "avg_power": 965,
          "max_power": 1050,
          "avg_hr": 111,
          "max_hr": 117,
          "avg_cadence": 99.6,
          "zone": 7,
          "training_load": 0.105578616,
          "decoupling": 17.886395
        },
        {
          "type": "RECOVERY",
          "duration_secs": 64,
          "avg_power": 148,
          "max_power": 674,
          "avg_hr": 116,
          "max_hr": 130,
          "avg_cadence": 51.265625,
          "zone": 1,
          "training_load": 1.146684,
          "decoupling": -26.266703
        },
        {
          "type": "WORK",
          "label": "7s@923w104rpm",
          "duration_secs": 8,
          "avg_power": 995,
          "max_power": 1192,
          "avg_hr": 123,
          "max_hr": 128,
          "avg_cadence": 105.125,
          "zone": 7,
          "training_load": 0.35245007,
          "decoupling": 24.560041
        },
        {
          "type": "RECOVERY",
          "duration_secs": 263,
          "avg_power": 155,
          "max_power": 737,
          "avg_hr": 115,
          "max_hr": 142,
          "avg_cadence": 82.73764,
          "zone": 1,
          "training_load": 4.972344,
          "decoupling": -0.3637278
        },
        {
          "type": "WORK",
          "label": "7s@923w104rpm",
          "duration_secs": 9,
          "avg_power": 925,
          "max_power": 1066,
          "avg_hr": 115,
          "max_hr": 122,
          "avg_cadence": 100.333336,
          "zone": 7,
          "training_load": 0.25628906,
          "decoupling": 11.269593
        },
        {
          "type": "RECOVERY",
          "duration_secs": 65,
          "avg_power": 189,
          "max_power": 754,
          "avg_hr": 132,
          "max_hr": 137,
          "avg_cadence": 82.50769,
          "zone": 2,
          "training_load": 1.6510254,
          "decoupling": -25.746382
        },
        {
          "type": "WORK",
          "label": "7s@923w104rpm",
          "duration_secs": 9,
          "avg_power": 812,
          "max_power": 974,
          "avg_hr": 131,
          "max_hr": 136,
          "avg_cadence": 110.55556,
          "zone": 7,
          "training_load": 0.29907227,
          "decoupling": 22.763844
        },
        {
          "type": "RECOVERY",
          "duration_secs": 63,
          "avg_power": 234,
          "max_power": 1021,
          "avg_hr": 143,
          "max_hr": 146,
          "avg_cadence": 77.333336,
          "zone": 2,
          "training_load": 1.7281934,
          "decoupling": -20.455877
        },
        {
          "type": "WORK",
          "label": "7s@923w104rpm",
          "duration_secs": 9,
          "avg_power": 1059,
          "max_power": 1282,
          "avg_hr": 143,
          "max_hr": 145,
          "avg_cadence": 111.888885,
          "zone": 7,
          "training_load": 0.50099856,
          "decoupling": 20.600588
        },
        {
          "type": "RECOVERY",
          "duration_secs": 248,
          "avg_power": 227,
          "max_power": 1145,
          "avg_hr": 132,
          "max_hr": 149,
          "avg_cadence": 77.40726,
          "zone": 2,
          "training_load": 6.38191,
          "decoupling": -13.814425
        },
        {
          "type": "WORK",
          "label": "7s@923w104rpm",
          "duration_secs": 8,
          "avg_power": 1051,
          "max_power": 1252,
          "avg_hr": 132,
          "max_hr": 137,
          "avg_cadence": 110.375,
          "zone": 7,
          "training_load": 0.37015843,
          "decoupling": 23.227678
        },
        {
          "type": "RECOVERY",
          "duration_secs": 63,
          "avg_power": 202,
          "max_power": 805,
          "avg_hr": 145,
          "max_hr": 151,
          "avg_cadence": 69.7619,
          "zone": 2,
          "training_load": 2.4807787,
          "decoupling": 0.27791166
        },
        {
          "type": "WORK",
          "label": "7s@923w104rpm",
          "duration_secs": 10,
          "avg_power": 846,
          "max_power": 938,
          "avg_hr": 141,
          "max_hr": 144,
          "avg_cadence": 103.3,
          "zone": 7,
          "training_load": 0.3653673,
          "decoupling": 15.524814
        },
        {
          "type": "RECOVERY",
          "duration_secs": 63,
          "avg_power": 185,
          "max_power": 897,
          "avg_hr": 141,
          "max_hr": 148,
          "avg_cadence": 76.77778,
          "zone": 2,
          "training_load": 1.8162402,
          "decoupling": -57.24985
        },
        {
          "type": "WORK",
          "label": "7s@923w104rpm",
          "duration_secs": 7,
          "avg_power": 853,
          "max_power": 1002,
          "avg_hr": 133,
          "max_hr": 136,
          "avg_cadence": 104.57143,
          "zone": 7,
          "training_load": 0.22080268,
          "decoupling": 22.251848
        },
        {
          "type": "RECOVERY",
          "duration_secs": 151,
          "avg_power": 169,
          "max_power": 684,
          "avg_hr": 131,
          "max_hr": 143,
          "avg_cadence": 76.4702,
          "zone": 1,
          "training_load": 2.539646,
          "decoupling": 0.26515955
        },
        {
          "type": "WORK",
          "label": "185s@248w91rpm",
          "duration_secs": 181,
          "avg_power": 249,
          "max_power": 332,
          "avg_hr": 130,
          "max_hr": 137,
          "avg_cadence": 87.8011,
          "zone": 3,
          "training_load": 2.971299,
          "decoupling": 11.808902
        },
        {
          "type": "RECOVERY",
          "duration_secs": 452,
          "avg_power": 217,
          "max_power": 488,
          "avg_hr": 130,
          "max_hr": 140,
          "avg_cadence": 83.108406,
          "zone": 2,
          "training_load": 6.656529,
          "decoupling": 4.244853
        },
        {
          "type": "WORK",
          "label": "292s@248w96rpm",
          "duration_secs": 292,
          "avg_power": 248,
          "max_power": 365,
          "avg_hr": 136,
          "max_hr": 144,
          "avg_cadence": 95.83219,
          "zone": 3,
          "training_load": 4.9111037,
          "decoupling": -8.923651
        },
        {
          "type": "RECOVERY",
          "duration_secs": 1116,
          "avg_power": 228,
          "max_power": 719,
          "avg_hr": 131,
          "max_hr": 148,
          "avg_cadence": 89.036736,
          "zone": 2,
          "training_load": 16.718506,
          "decoupling": -0.029089933
        },
        {
          "type": "WORK",
          "label": "7s@923w104rpm",
          "duration_secs": 7,
          "avg_power": 785,
          "max_power": 910,
          "avg_hr": 135,
          "max_hr": 138,
          "avg_cadence": 90.28571,
          "zone": 7,
          "training_load": 0.22996093,
          "decoupling": 14.556456
        },
        {
          "type": "RECOVERY",
          "duration_secs": 49,
          "avg_power": 180,
          "max_power": 699,
          "avg_hr": 142,
          "max_hr": 145,
          "avg_cadence": 94.67347,
          "zone": 2,
          "training_load": 1.2939062,
          "decoupling": 4.6710668
        },
        {
          "type": "WORK",
          "label": "185s@248w91rpm",
          "duration_secs": 189,
          "avg_power": 246,
          "max_power": 306,
          "avg_hr": 137,
          "max_hr": 146,
          "avg_cadence": 93.84656,
          "zone": 3,
          "training_load": 3.0274146,
          "decoupling": 1.9914184
        },
        {
          "type": "RECOVERY",
          "duration_secs": 272,
          "avg_power": 251,
          "max_power": 1054,
          "avg_hr": 139,
          "max_hr": 151,
          "avg_cadence": 87.79412,
          "zone": 3,
          "training_load": 5.458889,
          "decoupling": 0.014297215
        },
        {
          "type": "WORK",
          "label": "222s@253w94rpm",
          "duration_secs": 222,
          "avg_power": 253,
          "max_power": 355,
          "avg_hr": 140,
          "max_hr": 151,
          "avg_cadence": 94.4054,
          "zone": 3,
          "training_load": 3.7940056,
          "decoupling": -3.577366
        },
        {
          "type": "RECOVERY",
          "duration_secs": 249,
          "avg_power": 268,
          "max_power": 1279,
          "avg_hr": 144,
          "max_hr": 151,
          "avg_cadence": 96.78715,
          "zone": 3,
          "training_load": 5.5249577,
          "decoupling": 7.4032445
        },
        {
          "type": "WORK",
          "label": "7s@923w104rpm",
          "duration_secs": 7,
          "avg_power": 952,
          "max_power": 1090,
          "avg_hr": 139,
          "max_hr": 142,
          "avg_cadence": 108.71429,
          "zone": 7,
          "training_load": 0.28733915,
          "decoupling": 15.648404
        },
        {
          "type": "RECOVERY",
          "duration_secs": 240,
          "avg_power": 237,
          "max_power": 757,
          "avg_hr": 138,
          "max_hr": 150,
          "avg_cadence": 89.379166,
          "zone": 2,
          "training_load": 4.9953775,
          "decoupling": -17.105118
        },
        {
          "type": "WORK",
          "label": "7s@923w104rpm",
          "duration_secs": 6,
          "avg_power": 953,
          "max_power": 1104,
          "avg_hr": 136,
          "max_hr": 138,
          "avg_cadence": 103.333336,
          "zone": 7,
          "training_load": 0.2325586,
          "decoupling": 18.999598
        },
        {
          "type": "RECOVERY",
          "duration_secs": 245,
          "avg_power": 258,
          "max_power": 830,
          "avg_hr": 139,
          "max_hr": 150,
          "avg_cadence": 82.12245,
          "zone": 3,
          "training_load": 5.474285,
          "decoupling": -15.947572
        },
        {
          "type": "WORK",
          "label": "7s@923w104rpm",
          "duration_secs": 6,
          "avg_power": 938,
          "max_power": 1027,
          "avg_hr": 142,
          "max_hr": 144,
          "avg_cadence": 104.166664,
          "zone": 7,
          "training_load": 0.26433757,
          "decoupling": 14.962663
        },
        {
          "type": "RECOVERY",
          "duration_secs": 1018,
          "avg_power": 162,
          "max_power": 831,
          "avg_hr": 119,
          "max_hr": 146,
          "avg_cadence": 73.66437,
          "zone": 1,
          "training_load": 13.110869,
          "decoupling": 1.4733037
        }
      ]
    },
    {
      "activity_id": "i147814222",
      "date": "2026-05-13",
      "type": "Ride",
      "name": "Calonge - Threshold",
      "interval_summary": [
        "1x 5m38s 294w",
        "2x 3m36s 281w",
        "2x 4m24s 289w",
        "2x 12m23s 287w"
      ],
      "intervals": [
        {
          "type": "RECOVERY",
          "duration_secs": 963,
          "avg_power": 175,
          "max_power": 393,
          "avg_hr": 118,
          "max_hr": 135,
          "avg_cadence": 86.66332,
          "zone": 1,
          "training_load": 8.337145,
          "decoupling": 0.39318016
        },
        {
          "type": "WORK",
          "label": "338s@294w89rpm",
          "duration_secs": 338,
          "avg_power": 294,
          "max_power": 369,
          "avg_hr": 146,
          "max_hr": 152,
          "avg_cadence": 89.45858,
          "zone": 4,
          "training_load": 7.817717,
          "decoupling": 3.1451147
        },
        {
          "type": "RECOVERY",
          "duration_secs": 78,
          "avg_power": 308,
          "max_power": 411,
          "avg_hr": 150,
          "max_hr": 154,
          "avg_cadence": 86.410255,
          "zone": 4,
          "training_load": 1.9554167,
          "decoupling": -19.187847
        },
        {
          "type": "WORK",
          "label": "216s@281w89rpm",
          "duration_secs": 221,
          "avg_power": 291,
          "max_power": 386,
          "avg_hr": 150,
          "max_hr": 156,
          "avg_cadence": 89.75113,
          "zone": 4,
          "training_load": 5.2881374,
          "decoupling": -0.77606684
        },
        {
          "type": "RECOVERY",
          "duration_secs": 238,
          "avg_power": 215,
          "max_power": 537,
          "avg_hr": 137,
          "max_hr": 152,
          "avg_cadence": 70.36555,
          "zone": 2,
          "training_load": 3.9388406,
          "decoupling": -14.977578
        },
        {
          "type": "WORK",
          "label": "264s@289w90rpm",
          "duration_secs": 268,
          "avg_power": 287,
          "max_power": 482,
          "avg_hr": 144,
          "max_hr": 150,
          "avg_cadence": 91.022385,
          "zone": 3,
          "training_load": 6.03,
          "decoupling": 2.3905647
        },
        {
          "type": "RECOVERY",
          "duration_secs": 573,
          "avg_power": 156,
          "max_power": 392,
          "avg_hr": 115,
          "max_hr": 146,
          "avg_cadence": 81.64798,
          "zone": 1,
          "training_load": 4.205709,
          "decoupling": -15.839057
        },
        {
          "type": "WORK",
          "label": "743s@287w94rpm",
          "duration_secs": 744,
          "avg_power": 283,
          "max_power": 415,
          "avg_hr": 147,
          "max_hr": 156,
          "avg_cadence": 95.63844,
          "zone": 3,
          "training_load": 16.163795,
          "decoupling": 6.684243
        },
        {
          "type": "RECOVERY",
          "duration_secs": 13,
          "avg_power": 98,
          "max_power": 372,
          "avg_hr": 141,
          "max_hr": 145,
          "avg_cadence": 50.53846,
          "zone": 1,
          "training_load": 0.22572619,
          "decoupling": -8.653955
        },
        {
          "type": "WORK",
          "label": "743s@287w94rpm",
          "duration_secs": 742,
          "avg_power": 291,
          "max_power": 489,
          "avg_hr": 149,
          "max_hr": 158,
          "avg_cadence": 93.2062,
          "zone": 4,
          "training_load": 17.044624,
          "decoupling": 3.9489038
        },
        {
          "type": "RECOVERY",
          "duration_secs": 101,
          "avg_power": 250,
          "max_power": 373,
          "avg_hr": 140,
          "max_hr": 143,
          "avg_cadence": 88.10891,
          "zone": 3,
          "training_load": 1.8237207,
          "decoupling": -8.5520115
        },
        {
          "type": "WORK",
          "label": "264s@289w90rpm",
          "duration_secs": 260,
          "avg_power": 290,
          "max_power": 373,
          "avg_hr": 146,
          "max_hr": 153,
          "avg_cadence": 89.16538,
          "zone": 4,
          "training_load": 5.85,
          "decoupling": 1.9094008
        },
        {
          "type": "RECOVERY",
          "duration_secs": 50,
          "avg_power": 259,
          "max_power": 377,
          "avg_hr": 149,
          "max_hr": 151,
          "avg_cadence": 87.02,
          "zone": 3,
          "training_load": 0.99610734,
          "decoupling": -10.510315
        },
        {
          "type": "WORK",
          "label": "216s@281w89rpm",
          "duration_secs": 211,
          "avg_power": 271,
          "max_power": 374,
          "avg_hr": 145,
          "max_hr": 148,
          "avg_cadence": 88.32701,
          "zone": 3,
          "training_load": 4.2035728,
          "decoupling": -1.0803009
        },
        {
          "type": "RECOVERY",
          "duration_secs": 4449,
          "avg_power": 137,
          "max_power": 993,
          "avg_hr": 112,
          "max_hr": 148,
          "avg_cadence": 69.618805,
          "zone": 1,
          "training_load": 40.129257,
          "decoupling": -26.25352
        }
      ]
    },
    {
      "activity_id": "i150262083",
      "date": "2026-05-21",
      "type": "Ride",
      "name": "Horten Maantiepy\u00f6r\u00e4ily",
      "interval_summary": null,
      "intervals": [
        {
          "type": "RECOVERY",
          "duration_secs": 3104,
          "avg_power": 165,
          "max_power": 675,
          "avg_hr": 123,
          "max_hr": 154,
          "avg_cadence": 86.18947,
          "zone": 1,
          "training_load": 28.604391,
          "decoupling": 8.130011
        }
      ]
    },
    {
      "activity_id": "i150357150",
      "date": "2026-05-21",
      "type": "Ride",
      "name": "Horten Maantiepy\u00f6r\u00e4ily",
      "interval_summary": [
        "1x 18s 656w"
      ],
      "intervals": [
        {
          "type": "RECOVERY",
          "duration_secs": 3350,
          "avg_power": 143,
          "max_power": 912,
          "avg_hr": 114,
          "max_hr": 151,
          "avg_cadence": 76.45791,
          "zone": 1,
          "training_load": 31.777927,
          "decoupling": 2.1919844
        },
        {
          "type": "WORK",
          "label": "18s@656w101rpm",
          "duration_secs": 18,
          "avg_power": 656,
          "max_power": 795,
          "avg_hr": 136,
          "max_hr": 148,
          "avg_cadence": 101.0,
          "zone": 7,
          "training_load": 0.8328564,
          "decoupling": -14.706125
        },
        {
          "type": "RECOVERY",
          "duration_secs": 1156,
          "avg_power": 96,
          "max_power": 648,
          "avg_hr": 108,
          "max_hr": 148,
          "avg_cadence": 64.07937,
          "zone": 1,
          "training_load": 10.216468,
          "decoupling": 17.889193
        }
      ]
    },
    {
      "activity_id": "i150590432",
      "date": "2026-05-22",
      "type": "Ride",
      "name": "Horten Maantiepy\u00f6r\u00e4ily",
      "interval_summary": [
        "1x 3m45s 246w"
      ],
      "intervals": [
        {
          "type": "RECOVERY",
          "duration_secs": 4669,
          "avg_power": 177,
          "max_power": 600,
          "avg_hr": 120,
          "max_hr": 147,
          "avg_cadence": 81.98409,
          "zone": 2,
          "training_load": 47.121605,
          "decoupling": 0.9855338
        },
        {
          "type": "WORK",
          "label": "225s@246w93rpm",
          "duration_secs": 225,
          "avg_power": 246,
          "max_power": 385,
          "avg_hr": 135,
          "max_hr": 143,
          "avg_cadence": 92.67555,
          "zone": 3,
          "training_load": 3.574463,
          "decoupling": 3.8730433
        },
        {
          "type": "RECOVERY",
          "duration_secs": 389,
          "avg_power": 244,
          "max_power": 709,
          "avg_hr": 144,
          "max_hr": 158,
          "avg_cadence": 86.946014,
          "zone": 3,
          "training_load": 7.1698537,
          "decoupling": -12.536601
        }
      ]
    },
    {
      "activity_id": "i150880611",
      "date": "2026-05-23",
      "type": "Ride",
      "name": "Oslo Maantiepy\u00f6r\u00e4ily",
      "interval_summary": null,
      "intervals": [
        {
          "type": "RECOVERY",
          "duration_secs": 3742,
          "avg_power": 170,
          "max_power": 674,
          "avg_hr": 106,
          "max_hr": 130,
          "avg_cadence": 77.868195,
          "zone": 1,
          "training_load": 36.12963,
          "decoupling": -0.9159782
        }
      ]
    },
    {
      "activity_id": "i151132384",
      "date": "2026-05-24",
      "type": "Ride",
      "name": "Oslo Maantiepy\u00f6r\u00e4ily",
      "interval_summary": [
        "3x 10s 623w",
        "1x 3m35s 257w",
        "1x 14s 974w",
        "1x 19s 498w",
        "1x 1m47s 328w"
      ],
      "intervals": [
        {
          "type": "RECOVERY",
          "duration_secs": 2308,
          "avg_power": 112,
          "max_power": 543,
          "avg_hr": 102,
          "max_hr": 131,
          "avg_cadence": 64.71441,
          "zone": 1,
          "training_load": 13.815401,
          "decoupling": 0.5954217
        },
        {
          "type": "WORK",
          "label": "10s@623w91rpm",
          "duration_secs": 8,
          "avg_power": 607,
          "max_power": 691,
          "avg_hr": 126,
          "max_hr": 129,
          "avg_cadence": 84.875,
          "zone": 7,
          "training_load": 0.08083551,
          "decoupling": 11.549977
        },
        {
          "type": "RECOVERY",
          "duration_secs": 10004,
          "avg_power": 156,
          "max_power": 963,
          "avg_hr": 112,
          "max_hr": 145,
          "avg_cadence": 64.700264,
          "zone": 1,
          "training_load": 86.62367,
          "decoupling": -1.229925
        },
        {
          "type": "WORK",
          "label": "215s@257w92rpm",
          "duration_secs": 215,
          "avg_power": 257,
          "max_power": 391,
          "avg_hr": 132,
          "max_hr": 139,
          "avg_cadence": 92.093025,
          "zone": 3,
          "training_load": 3.8521416,
          "decoupling": 7.341794
        },
        {
          "type": "RECOVERY",
          "duration_secs": 4444,
          "avg_power": 118,
          "max_power": 1338,
          "avg_hr": 109,
          "max_hr": 157,
          "avg_cadence": 62.40327,
          "zone": 1,
          "training_load": 40.15212,
          "decoupling": -30.281898
        },
        {
          "type": "WORK",
          "label": "10s@623w91rpm",
          "duration_secs": 10,
          "avg_power": 602,
          "max_power": 707,
          "avg_hr": 127,
          "max_hr": 134,
          "avg_cadence": 99.3,
          "zone": 7,
          "training_load": 0.25566676,
          "decoupling": -1.4225576
        },
        {
          "type": "RECOVERY",
          "duration_secs": 6382,
          "avg_power": 133,
          "max_power": 1056,
          "avg_hr": 113,
          "max_hr": 147,
          "avg_cadence": 57.330032,
          "zone": 1,
          "training_load": 34.13212
        },
        {
          "type": "WORK",
          "label": "10s@623w91rpm",
          "duration_secs": 11,
          "avg_power": 661,
          "max_power": 834,
          "avg_hr": 121,
          "max_hr": 132,
          "avg_cadence": 89.09091,
          "zone": 7,
          "training_load": 0.16478814,
          "decoupling": 26.125982
        },
        {
          "type": "RECOVERY",
          "duration_secs": 2034,
          "avg_power": 135,
          "max_power": 914,
          "avg_hr": 111,
          "max_hr": 144,
          "avg_cadence": 63.520325,
          "zone": 1,
          "training_load": 13.463188
        },
        {
          "type": "WORK",
          "label": "14s@974w107rpm",
          "duration_secs": 14,
          "avg_power": 974,
          "max_power": 1183,
          "avg_hr": 133,
          "max_hr": 145,
          "avg_cadence": 107.35714,
          "zone": 7,
          "training_load": 0.9955556,
          "decoupling": -5.540268
        },
        {
          "type": "RECOVERY",
          "duration_secs": 2235,
          "avg_power": 209,
          "max_power": 783,
          "avg_hr": 130,
          "max_hr": 156,
          "avg_cadence": 83.41554,
          "zone": 2,
          "training_load": 39.452034,
          "decoupling": -25.153612
        },
        {
          "type": "WORK",
          "label": "19s@498w96rpm",
          "duration_secs": 19,
          "avg_power": 498,
          "max_power": 633,
          "avg_hr": 138,
          "max_hr": 144,
          "avg_cadence": 95.947365,
          "zone": 7,
          "training_load": 0.50171876,
          "decoupling": 4.353886
        },
        {
          "type": "RECOVERY",
          "duration_secs": 759,
          "avg_power": 198,
          "max_power": 1561,
          "avg_hr": 131,
          "max_hr": 150,
          "avg_cadence": 79.87125,
          "zone": 2,
          "training_load": 5.207283
        },
        {
          "type": "WORK",
          "label": "107s@328w82rpm",
          "duration_secs": 107,
          "avg_power": 328,
          "max_power": 395,
          "avg_hr": 135,
          "max_hr": 146,
          "avg_cadence": 82.299065,
          "zone": 4,
          "training_load": 2.898381,
          "decoupling": 0.7739133
        },
        {
          "type": "RECOVERY",
          "duration_secs": 1433,
          "avg_power": 166,
          "max_power": 614,
          "avg_hr": 117,
          "max_hr": 146,
          "avg_cadence": 69.989494,
          "zone": 1,
          "training_load": 14.394895,
          "decoupling": -9.299528
        }
      ]
    }
  ]
}